fprs/__init__.py
fprs/parameters.py
fprs/robot.py
fprs/specification.py
fprs/specification_parameterizer.py
fprs-1.0.0.dist-info/LICENSE
fprs-1.0.0.dist-info/METADATA
fprs-1.0.0.dist-info/WHEEL
fprs-1.0.0.dist-info/top_level.txt
fprs-1.0.0.dist-info/RECORD
