Metadata-Version: 2.1
Name: fprs
Version: 1.0.0
Summary: Framework for Parameterized Robot Specifications (FPRS).
Home-page: https://github.com/Co-Evolve/fprs
Author-email: Dries Marzougui <dries.marzougui@gmail.com>
License: MIT
Project-URL: Homepage, https://github.com/Co-Evolve/fprs
Project-URL: Repository, https://github.com/Co-Evolve/fprs
Classifier: Development Status :: 5 - Production/Stable
Classifier: Intended Audience :: Developers
Classifier: Intended Audience :: Science/Research
Classifier: Natural Language :: English
Classifier: Programming Language :: Python :: 3
Classifier: Programming Language :: Python :: 3.8
Classifier: Programming Language :: Python :: 3.9
Classifier: Programming Language :: Python :: 3.10
Classifier: Programming Language :: Python :: 3.11
Classifier: Programming Language :: Python :: 3.12
Classifier: Topic :: Scientific/Engineering
Requires-Python: >=3.8
License-File: LICENSE
Requires-Dist: numpy
